gstat_exporter.py
gstat_exporter-0.2.0.dist-info/LICENSE
gstat_exporter-0.2.0.dist-info/METADATA
gstat_exporter-0.2.0.dist-info/WHEEL
gstat_exporter-0.2.0.dist-info/entry_points.txt
gstat_exporter-0.2.0.dist-info/top_level.txt
gstat_exporter-0.2.0.dist-info/RECORD
